commonlib/__init__.py
commonlib/models/__init__.py
commonlib/models/contest.py
commonlib/models/database.py
commonlib/models/llm.py
commonlib/models/matchmaking.py
commonlib/models/utility.py
commonlib/services/__init__.py
commonlib/services/contest.py
commonlib/services/llm.py
wizard_contest_commonlib-0.0.16.dist-info/METADATA
wizard_contest_commonlib-0.0.16.dist-info/WHEEL
wizard_contest_commonlib-0.0.16.dist-info/licenses/LICENSE
wizard_contest_commonlib-0.0.16.dist-info/RECORD
